certbot_dns_powerdns_bbr/__init__.py
certbot_dns_powerdns_bbr/dns_powerdns_bbr.py
certbot_dns_powerdns_bbr-0.1.2.dist-info/LICENSE
certbot_dns_powerdns_bbr-0.1.2.dist-info/METADATA
certbot_dns_powerdns_bbr-0.1.2.dist-info/WHEEL
certbot_dns_powerdns_bbr-0.1.2.dist-info/entry_points.txt
certbot_dns_powerdns_bbr-0.1.2.dist-info/RECORD
