Metadata-Version: 2.1
Name: certbot-dns-powerdns-bbr
Version: 0.1.2
Summary: certbot PowerDNS Remote REST API Authenticator
Home-page: https://github.com/bugbearr/certbot-dns-powerdns-bbr
License: MIT
Author: BugbearR
Author-email: bugbearr@bugbearr.jp
Requires-Python: >=3.9,<4.0
Classifier: Development Status :: 4 - Beta
Classifier: Environment :: Plugins
Classifier: Intended Audience :: System Administrators
Classifier: License :: OSI Approved :: MIT License
Classifier: Operating System :: POSIX :: Linux
Classifier: Programming Language :: Python
Classifier: Programming Language :: Python :: 3
Classifier: Programming Language :: Python :: 3.9
Classifier: Programming Language :: Python :: 3.10
Classifier: Programming Language :: Python :: 3.11
Classifier: Programming Language :: Python :: 3.12
Classifier: Topic :: Internet :: WWW/HTTP
Classifier: Topic :: Security
Classifier: Topic :: System :: Installation/Setup
Classifier: Topic :: System :: Networking
Classifier: Topic :: System :: Systems Administration
Classifier: Topic :: Utilities
Requires-Dist: certbot (>=2.7.4,<3.0.0)
Requires-Dist: requests (>=2.31.0,<3.0.0)
Requires-Dist: zope-interface (>=6.1,<7.0)
Project-URL: Repository, https://github.com/bugbearr/certbot-dns-powerdns-bbr
